syrabrox_errorviewer/__init__.py
syrabrox_errorviewer/main.py
syrabrox_errorviewer-1.1.0.dist-info/METADATA
syrabrox_errorviewer-1.1.0.dist-info/WHEEL
syrabrox_errorviewer-1.1.0.dist-info/entry_points.txt
syrabrox_errorviewer-1.1.0.dist-info/top_level.txt
syrabrox_errorviewer-1.1.0.dist-info/RECORD
