Metadata-Version: 2.1
Name: syrabrox_errorviewer
Version: 1.1.0
